cdmaoapi/__init__.py
cdmaoapi-2.0.0.dist-info/LICENSE
cdmaoapi-2.0.0.dist-info/METADATA
cdmaoapi-2.0.0.dist-info/WHEEL
cdmaoapi-2.0.0.dist-info/top_level.txt
cdmaoapi-2.0.0.dist-info/RECORD
