Metadata-Version: 2.1
Name: cdmaoapi
Version: 2.0.0
Summary: 获取/提交编程猫官方数据
Home-page: http://doc.viyrs.com/cdmaoapi.html
Author: 冷鱼闲风
Author-email: 2991883280@qq.com
License: UNKNOWN
Platform: UNKNOWN
Classifier: Programming Language :: Python
Classifier: Operating System :: OS Independent
Classifier: License :: OSI Approved :: Apache Software License
Requires-Dist: requests
